{"commitInfo":{"timestamp":1778447961405,"operation":"STREAMING UPDATE","operationParameters":{"outputMode":"Complete","queryId":"b19e9621-fb02-4352-a714-aa3789e32538","epochId":"37"},"readVersion":36,"isolationLevel":"Serializable","isBlindAppend":false,"operationMetrics":{"numRemovedFiles":"35","numOutputRows":"38","numOutputBytes":"53826","numAddedFiles":"36"},"engineInfo":"Apache-Spark/3.5.6 Delta-Lake/3.2.0","txnId":"fb8fb465-eebb-4e78-913d-0e9057bd721f"}}
{"txn":{"appId":"b19e9621-fb02-4352-a714-aa3789e32538","version":37,"lastUpdated":1778447961404}}
{"add":{"path":"part-00002-0e3600cf-c9b0-440a-b452-75cb5c906111-c000.snappy.parquet","partitionValues":{},"size":1478,"modificationTime":1778447926788,"dataChange":true,"stats":"{\"numRecords\":1,\"minValues\":{\"window\":{\"start\":\"2026-05-10T21:11:00.000Z\",\"end\":\"2026-05-10T21:12:00.000Z\"},\"olay_tipi\":\"purchase\",\"count\":6955},\"maxValues\":{\"window\":{\"start\":\"2026-05-10T21:11:00.000Z\",\"end\":\"2026-05-10T21:12:00.000Z\"},\"olay_tipi\":\"purchase\",\"count\":6955},\"nullCount\":{\"window\":{\"start\":0,\"end\":0},\"olay_tipi\":0,\"count\":0}}"}}
{"add":{"path":"part-00009-44ece789-494d-4b72-9604-59e7e9b7bade-c000.snappy.parquet","partitionValues":{},"size":1477,"modificationTime":1778447927993,"dataChange":true,"stats":"{\"numRecords\":1,\"minValues\":{\"window\":{\"start\":\"2026-05-10T20:43:00.000Z\",\"end\":\"2026-05-10T20:44:00.000Z\"},\"olay_tipi\":\"purchase\",\"count\":11827},\"maxValues\":{\"window\":{\"start\":\"2026-05-10T20:43:00.000Z\",\"end\":\"2026-05-10T20:44:00.000Z\"},\"olay_tipi\":\"purchase\",\"count\":11827},\"nullCount\":{\"window\":{\"start\":0,\"end\":0},\"olay_tipi\":0,\"count\":0}}"}}
{"add":{"path":"part-00010-4b1b88a8-ab86-4a2b-8319-8eb45bc13e68-c000.snappy.parquet","partitionValues":{},"size":1478,"modificationTime":1778447928212,"dataChange":true,"stats":"{\"numRecords\":1,\"minValues\":{\"window\":{\"start\":\"2026-05-10T20:12:00.000Z\",\"end\":\"2026-05-10T20:13:00.000Z\"},\"olay_tipi\":\"purchase\",\"count\":12335},\"maxValues\":{\"window\":{\"start\":\"2026-05-10T20:12:00.000Z\",\"end\":\"2026-05-10T20:13:00.000Z\"},\"olay_tipi\":\"purchase\",\"count\":12335},\"nullCount\":{\"window\":{\"start\":0,\"end\":0},\"olay_tipi\":0,\"count\":0}}"}}
{"add":{"path":"part-00011-7ff9b39c-1193-47c9-953f-6a287279a537-c000.snappy.parquet","partitionValues":{},"size":1478,"modificationTime":1778447928424,"dataChange":true,"stats":"{\"numRecords\":1,\"minValues\":{\"window\":{\"start\":\"2026-05-10T20:41:00.000Z\",\"end\":\"2026-05-10T20:42:00.000Z\"},\"olay_tipi\":\"purchase\",\"count\":11402},\"maxValues\":{\"window\":{\"start\":\"2026-05-10T20:41:00.000Z\",\"end\":\"2026-05-10T20:42:00.000Z\"},\"olay_tipi\":\"purchase\",\"count\":11402},\"nullCount\":{\"window\":{\"start\":0,\"end\":0},\"olay_tipi\":0,\"count\":0}}"}}
{"add":{"path":"part-00017-efe94067-1474-4d5e-924f-316849f7a600-c000.snappy.parquet","partitionValues":{},"size":1436,"modificationTime":1778447929651,"dataChange":true,"stats":"{\"numRecords\":2,\"minValues\":{\"window\":{\"start\":\"2026-05-10T20:48:00.000Z\",\"end\":\"2026-05-10T20:49:00.000Z\"},\"olay_tipi\":\"purchase\",\"count\":11374},\"maxValues\":{\"window\":{\"start\":\"2026-05-10T20:52:00.000Z\",\"end\":\"2026-05-10T20:53:00.000Z\"},\"olay_tipi\":\"purchase\",\"count\":12060},\"nullCount\":{\"window\":{\"start\":0,\"end\":0},\"olay_tipi\":0,\"count\":0}}"}}
{"add":{"path":"part-00023-5cfd3faf-e1f5-4a07-9139-69cbb6c0a436-c000.snappy.parquet","partitionValues":{},"size":1477,"modificationTime":1778447931041,"dataChange":true,"stats":"{\"numRecords\":1,\"minValues\":{\"window\":{\"start\":\"2026-05-10T20:25:00.000Z\",\"end\":\"2026-05-10T20:26:00.000Z\"},\"olay_tipi\":\"purchase\",\"count\":15971},\"maxValues\":{\"window\":{\"start\":\"2026-05-10T20:25:00.000Z\",\"end\":\"2026-05-10T20:26:00.000Z\"},\"olay_tipi\":\"purchase\",\"count\":15971},\"nullCount\":{\"window\":{\"start\":0,\"end\":0},\"olay_tipi\":0,\"count\":0}}"}}
{"add":{"path":"part-00024-909077cc-8f75-4e5d-a04e-e3fe245fb371-c000.snappy.parquet","partitionValues":{},"size":1478,"modificationTime":1778447931313,"dataChange":true,"stats":"{\"numRecords\":1,\"minValues\":{\"window\":{\"start\":\"2026-05-10T19:57:00.000Z\",\"end\":\"2026-05-10T19:58:00.000Z\"},\"olay_tipi\":\"purchase\",\"count\":22121},\"maxValues\":{\"window\":{\"start\":\"2026-05-10T19:57:00.000Z\",\"end\":\"2026-05-10T19:58:00.000Z\"},\"olay_tipi\":\"purchase\",\"count\":22121},\"nullCount\":{\"window\":{\"start\":0,\"end\":0},\"olay_tipi\":0,\"count\":0}}"}}
{"add":{"path":"part-00029-1177f4e6-cebd-4ca5-bf2b-768aea41a0b1-c000.snappy.parquet","partitionValues":{},"size":1478,"modificationTime":1778447932491,"dataChange":true,"stats":"{\"numRecords\":1,\"minValues\":{\"window\":{\"start\":\"2026-05-10T21:13:00.000Z\",\"end\":\"2026-05-10T21:14:00.000Z\"},\"olay_tipi\":\"purchase\",\"count\":11537},\"maxValues\":{\"window\":{\"start\":\"2026-05-10T21:13:00.000Z\",\"end\":\"2026-05-10T21:14:00.000Z\"},\"olay_tipi\":\"purchase\",\"count\":11537},\"nullCount\":{\"window\":{\"start\":0,\"end\":0},\"olay_tipi\":0,\"count\":0}}"}}
{"add":{"path":"part-00049-6bb290c5-2a1e-49e9-a60f-416fa80e8212-c000.snappy.parquet","partitionValues":{},"size":1478,"modificationTime":1778447935860,"dataChange":true,"stats":"{\"numRecords\":1,\"minValues\":{\"window\":{\"start\":\"2026-05-10T21:07:00.000Z\",\"end\":\"2026-05-10T21:08:00.000Z\"},\"olay_tipi\":\"purchase\",\"count\":12355},\"maxValues\":{\"window\":{\"start\":\"2026-05-10T21:07:00.000Z\",\"end\":\"2026-05-10T21:08:00.000Z\"},\"olay_tipi\":\"purchase\",\"count\":12355},\"nullCount\":{\"window\":{\"start\":0,\"end\":0},\"olay_tipi\":0,\"count\":0}}"}}
{"add":{"path":"part-00062-5b0200ee-3422-474e-a5f1-502e057c9f70-c000.snappy.parquet","partitionValues":{},"size":1478,"modificationTime":1778447937615,"dataChange":true,"stats":"{\"numRecords\":1,\"minValues\":{\"window\":{\"start\":\"2026-05-10T20:50:00.000Z\",\"end\":\"2026-05-10T20:51:00.000Z\"},\"olay_tipi\":\"purchase\",\"count\":11339},\"maxValues\":{\"window\":{\"start\":\"2026-05-10T20:50:00.000Z\",\"end\":\"2026-05-10T20:51:00.000Z\"},\"olay_tipi\":\"purchase\",\"count\":11339},\"nullCount\":{\"window\":{\"start\":0,\"end\":0},\"olay_tipi\":0,\"count\":0}}"}}
{"add":{"path":"part-00065-75afa207-4ac3-4751-90f6-3b08503218f1-c000.snappy.parquet","partitionValues":{},"size":1477,"modificationTime":1778447938098,"dataChange":true,"stats":"{\"numRecords\":1,\"minValues\":{\"window\":{\"start\":\"2026-05-10T20:31:00.000Z\",\"end\":\"2026-05-10T20:32:00.000Z\"},\"olay_tipi\":\"purchase\",\"count\":12338},\"maxValues\":{\"window\":{\"start\":\"2026-05-10T20:31:00.000Z\",\"end\":\"2026-05-10T20:32:00.000Z\"},\"olay_tipi\":\"purchase\",\"count\":12338},\"nullCount\":{\"window\":{\"start\":0,\"end\":0},\"olay_tipi\":0,\"count\":0}}"}}
{"add":{"path":"part-00075-01e8313b-7074-476a-a18a-5ac8362cb4e8-c000.snappy.parquet","partitionValues":{},"size":1478,"modificationTime":1778447939817,"dataChange":true,"stats":"{\"numRecords\":1,\"minValues\":{\"window\":{\"start\":\"2026-05-10T19:50:00.000Z\",\"end\":\"2026-05-10T19:51:00.000Z\"},\"olay_tipi\":\"purchase\",\"count\":23991},\"maxValues\":{\"window\":{\"start\":\"2026-05-10T19:50:00.000Z\",\"end\":\"2026-05-10T19:51:00.000Z\"},\"olay_tipi\":\"purchase\",\"count\":23991},\"nullCount\":{\"window\":{\"start\":0,\"end\":0},\"olay_tipi\":0,\"count\":0}}"}}
{"add":{"path":"part-00079-12d51652-eeda-49f2-a1c4-c4c88e6fe422-c000.snappy.parquet","partitionValues":{},"size":1478,"modificationTime":1778447940627,"dataChange":true,"stats":"{\"numRecords\":1,\"minValues\":{\"window\":{\"start\":\"2026-05-10T21:17:00.000Z\",\"end\":\"2026-05-10T21:18:00.000Z\"},\"olay_tipi\":\"purchase\",\"count\":10612},\"maxValues\":{\"window\":{\"start\":\"2026-05-10T21:17:00.000Z\",\"end\":\"2026-05-10T21:18:00.000Z\"},\"olay_tipi\":\"purchase\",\"count\":10612},\"nullCount\":{\"window\":{\"start\":0,\"end\":0},\"olay_tipi\":0,\"count\":0}}"}}
{"add":{"path":"part-00083-33a196d6-3042-429d-a470-a354d35e30e2-c000.snappy.parquet","partitionValues":{},"size":1478,"modificationTime":1778447941469,"dataChange":true,"stats":"{\"numRecords\":1,\"minValues\":{\"window\":{\"start\":\"2026-05-10T20:36:00.000Z\",\"end\":\"2026-05-10T20:37:00.000Z\"},\"olay_tipi\":\"purchase\",\"count\":11996},\"maxValues\":{\"window\":{\"start\":\"2026-05-10T20:36:00.000Z\",\"end\":\"2026-05-10T20:37:00.000Z\"},\"olay_tipi\":\"purchase\",\"count\":11996},\"nullCount\":{\"window\":{\"start\":0,\"end\":0},\"olay_tipi\":0,\"count\":0}}"}}
{"add":{"path":"part-00086-50fe2980-2dea-4552-9df3-a6314cdc45ef-c000.snappy.parquet","partitionValues":{},"size":1478,"modificationTime":1778447942298,"dataChange":true,"stats":"{\"numRecords\":1,\"minValues\":{\"window\":{\"start\":\"2026-05-10T20:33:00.000Z\",\"end\":\"2026-05-10T20:34:00.000Z\"},\"olay_tipi\":\"purchase\",\"count\":12483},\"maxValues\":{\"window\":{\"start\":\"2026-05-10T20:33:00.000Z\",\"end\":\"2026-05-10T20:34:00.000Z\"},\"olay_tipi\":\"purchase\",\"count\":12483},\"nullCount\":{\"window\":{\"start\":0,\"end\":0},\"olay_tipi\":0,\"count\":0}}"}}
{"add":{"path":"part-00102-4d45030a-54fd-4249-a443-f882515f4eee-c000.snappy.parquet","partitionValues":{},"size":1478,"modificationTime":1778447944526,"dataChange":true,"stats":"{\"numRecords\":1,\"minValues\":{\"window\":{\"start\":\"2026-05-10T19:53:00.000Z\",\"end\":\"2026-05-10T19:54:00.000Z\"},\"olay_tipi\":\"purchase\",\"count\":18397},\"maxValues\":{\"window\":{\"start\":\"2026-05-10T19:53:00.000Z\",\"end\":\"2026-05-10T19:54:00.000Z\"},\"olay_tipi\":\"purchase\",\"count\":18397},\"nullCount\":{\"window\":{\"start\":0,\"end\":0},\"olay_tipi\":0,\"count\":0}}"}}
{"add":{"path":"part-00105-8ab45eec-ea0b-4200-a421-c0ca5ab9e874-c000.snappy.parquet","partitionValues":{},"size":1478,"modificationTime":1778447945013,"dataChange":true,"stats":"{\"numRecords\":1,\"minValues\":{\"window\":{\"start\":\"2026-05-10T21:01:00.000Z\",\"end\":\"2026-05-10T21:02:00.000Z\"},\"olay_tipi\":\"purchase\",\"count\":10945},\"maxValues\":{\"window\":{\"start\":\"2026-05-10T21:01:00.000Z\",\"end\":\"2026-05-10T21:02:00.000Z\"},\"olay_tipi\":\"purchase\",\"count\":10945},\"nullCount\":{\"window\":{\"start\":0,\"end\":0},\"olay_tipi\":0,\"count\":0}}"}}
{"add":{"path":"part-00107-4f20a77a-b105-4940-9179-51bd5c4588c3-c000.snappy.parquet","partitionValues":{},"size":1478,"modificationTime":1778447945366,"dataChange":true,"stats":"{\"numRecords\":1,\"minValues\":{\"window\":{\"start\":\"2026-05-10T20:46:00.000Z\",\"end\":\"2026-05-10T20:47:00.000Z\"},\"olay_tipi\":\"purchase\",\"count\":13277},\"maxValues\":{\"window\":{\"start\":\"2026-05-10T20:46:00.000Z\",\"end\":\"2026-05-10T20:47:00.000Z\"},\"olay_tipi\":\"purchase\",\"count\":13277},\"nullCount\":{\"window\":{\"start\":0,\"end\":0},\"olay_tipi\":0,\"count\":0}}"}}
{"add":{"path":"part-00108-d0408119-c94c-4e03-ab27-7b9c35eddb47-c000.snappy.parquet","partitionValues":{},"size":1478,"modificationTime":1778447945593,"dataChange":true,"stats":"{\"numRecords\":1,\"minValues\":{\"window\":{\"start\":\"2026-05-10T20:58:00.000Z\",\"end\":\"2026-05-10T20:59:00.000Z\"},\"olay_tipi\":\"purchase\",\"count\":11236},\"maxValues\":{\"window\":{\"start\":\"2026-05-10T20:58:00.000Z\",\"end\":\"2026-05-10T20:59:00.000Z\"},\"olay_tipi\":\"purchase\",\"count\":11236},\"nullCount\":{\"window\":{\"start\":0,\"end\":0},\"olay_tipi\":0,\"count\":0}}"}}
{"add":{"path":"part-00119-7716f19d-2701-490b-bde6-9f23b91b38a5-c000.snappy.parquet","partitionValues":{},"size":1478,"modificationTime":1778447947797,"dataChange":true,"stats":"{\"numRecords\":1,\"minValues\":{\"window\":{\"start\":\"2026-05-10T20:22:00.000Z\",\"end\":\"2026-05-10T20:23:00.000Z\"},\"olay_tipi\":\"purchase\",\"count\":12103},\"maxValues\":{\"window\":{\"start\":\"2026-05-10T20:22:00.000Z\",\"end\":\"2026-05-10T20:23:00.000Z\"},\"olay_tipi\":\"purchase\",\"count\":12103},\"nullCount\":{\"window\":{\"start\":0,\"end\":0},\"olay_tipi\":0,\"count\":0}}"}}
{"add":{"path":"part-00124-6972ca9f-85e5-4ad1-bfa3-a473d2108f2f-c000.snappy.parquet","partitionValues":{},"size":1478,"modificationTime":1778447948878,"dataChange":true,"stats":"{\"numRecords\":1,\"minValues\":{\"window\":{\"start\":\"2026-05-10T20:00:00.000Z\",\"end\":\"2026-05-10T20:01:00.000Z\"},\"olay_tipi\":\"purchase\",\"count\":16152},\"maxValues\":{\"window\":{\"start\":\"2026-05-10T20:00:00.000Z\",\"end\":\"2026-05-10T20:01:00.000Z\"},\"olay_tipi\":\"purchase\",\"count\":16152},\"nullCount\":{\"window\":{\"start\":0,\"end\":0},\"olay_tipi\":0,\"count\":0}}"}}
{"add":{"path":"part-00131-272032c2-3086-439f-aca5-b2d7ad8d6cb7-c000.snappy.parquet","partitionValues":{},"size":1478,"modificationTime":1778447950244,"dataChange":true,"stats":"{\"numRecords\":1,\"minValues\":{\"window\":{\"start\":\"2026-05-10T20:29:00.000Z\",\"end\":\"2026-05-10T20:30:00.000Z\"},\"olay_tipi\":\"purchase\",\"count\":11576},\"maxValues\":{\"window\":{\"start\":\"2026-05-10T20:29:00.000Z\",\"end\":\"2026-05-10T20:30:00.000Z\"},\"olay_tipi\":\"purchase\",\"count\":11576},\"nullCount\":{\"window\":{\"start\":0,\"end\":0},\"olay_tipi\":0,\"count\":0}}"}}
{"add":{"path":"part-00142-3bf2c5e4-dc5f-46e3-a936-45fc6d24e898-c000.snappy.parquet","partitionValues":{},"size":1478,"modificationTime":1778447952084,"dataChange":true,"stats":"{\"numRecords\":1,\"minValues\":{\"window\":{\"start\":\"2026-05-10T20:15:00.000Z\",\"end\":\"2026-05-10T20:16:00.000Z\"},\"olay_tipi\":\"purchase\",\"count\":12090},\"maxValues\":{\"window\":{\"start\":\"2026-05-10T20:15:00.000Z\",\"end\":\"2026-05-10T20:16:00.000Z\"},\"olay_tipi\":\"purchase\",\"count\":12090},\"nullCount\":{\"window\":{\"start\":0,\"end\":0},\"olay_tipi\":0,\"count\":0}}"}}
{"add":{"path":"part-00157-a5f95999-c3cc-4961-bec0-5d00ba06983a-c000.snappy.parquet","partitionValues":{},"size":1478,"modificationTime":1778447954694,"dataChange":true,"stats":"{\"numRecords\":1,\"minValues\":{\"window\":{\"start\":\"2026-05-10T21:10:00.000Z\",\"end\":\"2026-05-10T21:11:00.000Z\"},\"olay_tipi\":\"purchase\",\"count\":16917},\"maxValues\":{\"window\":{\"start\":\"2026-05-10T21:10:00.000Z\",\"end\":\"2026-05-10T21:11:00.000Z\"},\"olay_tipi\":\"purchase\",\"count\":16917},\"nullCount\":{\"window\":{\"start\":0,\"end\":0},\"olay_tipi\":0,\"count\":0}}"}}
{"add":{"path":"part-00158-5ddaac54-5184-4974-bc8e-0ab8d3ef1f92-c000.snappy.parquet","partitionValues":{},"size":1478,"modificationTime":1778447954857,"dataChange":true,"stats":"{\"numRecords\":1,\"minValues\":{\"window\":{\"start\":\"2026-05-10T20:06:00.000Z\",\"end\":\"2026-05-10T20:07:00.000Z\"},\"olay_tipi\":\"purchase\",\"count\":16905},\"maxValues\":{\"window\":{\"start\":\"2026-05-10T20:06:00.000Z\",\"end\":\"2026-05-10T20:07:00.000Z\"},\"olay_tipi\":\"purchase\",\"count\":16905},\"nullCount\":{\"window\":{\"start\":0,\"end\":0},\"olay_tipi\":0,\"count\":0}}"}}
{"add":{"path":"part-00162-33afe22e-431f-439c-a320-973edbd101a1-c000.snappy.parquet","partitionValues":{},"size":1478,"modificationTime":1778447955419,"dataChange":true,"stats":"{\"numRecords\":1,\"minValues\":{\"window\":{\"start\":\"2026-05-10T20:02:00.000Z\",\"end\":\"2026-05-10T20:03:00.000Z\"},\"olay_tipi\":\"purchase\",\"count\":13828},\"maxValues\":{\"window\":{\"start\":\"2026-05-10T20:02:00.000Z\",\"end\":\"2026-05-10T20:03:00.000Z\"},\"olay_tipi\":\"purchase\",\"count\":13828},\"nullCount\":{\"window\":{\"start\":0,\"end\":0},\"olay_tipi\":0,\"count\":0}}"}}
{"add":{"path":"part-00166-442fcfe8-ade8-4a36-a826-3e261f49605b-c000.snappy.parquet","partitionValues":{},"size":1478,"modificationTime":1778447955968,"dataChange":true,"stats":"{\"numRecords\":1,\"minValues\":{\"window\":{\"start\":\"2026-05-10T20:17:00.000Z\",\"end\":\"2026-05-10T20:18:00.000Z\"},\"olay_tipi\":\"purchase\",\"count\":12804},\"maxValues\":{\"window\":{\"start\":\"2026-05-10T20:17:00.000Z\",\"end\":\"2026-05-10T20:18:00.000Z\"},\"olay_tipi\":\"purchase\",\"count\":12804},\"nullCount\":{\"window\":{\"start\":0,\"end\":0},\"olay_tipi\":0,\"count\":0}}"}}
{"add":{"path":"part-00167-4da8a74b-554b-4997-b99c-6fd3912cb4aa-c000.snappy.parquet","partitionValues":{},"size":1478,"modificationTime":1778447956150,"dataChange":true,"stats":"{\"numRecords\":1,\"minValues\":{\"window\":{\"start\":\"2026-05-10T20:08:00.000Z\",\"end\":\"2026-05-10T20:09:00.000Z\"},\"olay_tipi\":\"purchase\",\"count\":12685},\"maxValues\":{\"window\":{\"start\":\"2026-05-10T20:08:00.000Z\",\"end\":\"2026-05-10T20:09:00.000Z\"},\"olay_tipi\":\"purchase\",\"count\":12685},\"nullCount\":{\"window\":{\"start\":0,\"end\":0},\"olay_tipi\":0,\"count\":0}}"}}
{"add":{"path":"part-00177-7ce460ae-6fb4-47c7-89f7-283051f1a5fd-c000.snappy.parquet","partitionValues":{},"size":1478,"modificationTime":1778447957481,"dataChange":true,"stats":"{\"numRecords\":1,\"minValues\":{\"window\":{\"start\":\"2026-05-10T20:54:00.000Z\",\"end\":\"2026-05-10T20:55:00.000Z\"},\"olay_tipi\":\"purchase\",\"count\":10962},\"maxValues\":{\"window\":{\"start\":\"2026-05-10T20:54:00.000Z\",\"end\":\"2026-05-10T20:55:00.000Z\"},\"olay_tipi\":\"purchase\",\"count\":10962},\"nullCount\":{\"window\":{\"start\":0,\"end\":0},\"olay_tipi\":0,\"count\":0}}"}}
{"add":{"path":"part-00180-c570d24b-75e9-469d-bbb5-6a52ccddf695-c000.snappy.parquet","partitionValues":{},"size":1478,"modificationTime":1778447957961,"dataChange":true,"stats":"{\"numRecords\":1,\"minValues\":{\"window\":{\"start\":\"2026-05-10T20:27:00.000Z\",\"end\":\"2026-05-10T20:28:00.000Z\"},\"olay_tipi\":\"purchase\",\"count\":11747},\"maxValues\":{\"window\":{\"start\":\"2026-05-10T20:27:00.000Z\",\"end\":\"2026-05-10T20:28:00.000Z\"},\"olay_tipi\":\"purchase\",\"count\":11747},\"nullCount\":{\"window\":{\"start\":0,\"end\":0},\"olay_tipi\":0,\"count\":0}}"}}
{"add":{"path":"part-00187-15c0269d-7d5b-4ee7-9426-ec799a7178ae-c000.snappy.parquet","partitionValues":{},"size":1436,"modificationTime":1778447959048,"dataChange":true,"stats":"{\"numRecords\":2,\"minValues\":{\"window\":{\"start\":\"2026-05-10T20:10:00.000Z\",\"end\":\"2026-05-10T20:11:00.000Z\"},\"olay_tipi\":\"purchase\",\"count\":11151},\"maxValues\":{\"window\":{\"start\":\"2026-05-10T20:56:00.000Z\",\"end\":\"2026-05-10T20:57:00.000Z\"},\"olay_tipi\":\"purchase\",\"count\":13229},\"nullCount\":{\"window\":{\"start\":0,\"end\":0},\"olay_tipi\":0,\"count\":0}}"}}
{"add":{"path":"part-00189-0ff1a7a1-15dc-4190-b46e-4ac7a81c7353-c000.snappy.parquet","partitionValues":{},"size":1478,"modificationTime":1778447959422,"dataChange":true,"stats":"{\"numRecords\":1,\"minValues\":{\"window\":{\"start\":\"2026-05-10T21:15:00.000Z\",\"end\":\"2026-05-10T21:16:00.000Z\"},\"olay_tipi\":\"purchase\",\"count\":11454},\"maxValues\":{\"window\":{\"start\":\"2026-05-10T21:15:00.000Z\",\"end\":\"2026-05-10T21:16:00.000Z\"},\"olay_tipi\":\"purchase\",\"count\":11454},\"nullCount\":{\"window\":{\"start\":0,\"end\":0},\"olay_tipi\":0,\"count\":0}}"}}
{"add":{"path":"part-00191-bf8cba73-69ab-42bb-9290-f9bf60e1a8e0-c000.snappy.parquet","partitionValues":{},"size":1478,"modificationTime":1778447959791,"dataChange":true,"stats":"{\"numRecords\":1,\"minValues\":{\"window\":{\"start\":\"2026-05-10T20:20:00.000Z\",\"end\":\"2026-05-10T20:21:00.000Z\"},\"olay_tipi\":\"purchase\",\"count\":16863},\"maxValues\":{\"window\":{\"start\":\"2026-05-10T20:20:00.000Z\",\"end\":\"2026-05-10T20:21:00.000Z\"},\"olay_tipi\":\"purchase\",\"count\":16863},\"nullCount\":{\"window\":{\"start\":0,\"end\":0},\"olay_tipi\":0,\"count\":0}}"}}
{"add":{"path":"part-00192-b6bc39f7-04f9-4a5c-a36c-a3e440770a30-c000.snappy.parquet","partitionValues":{},"size":1478,"modificationTime":1778447959964,"dataChange":true,"stats":"{\"numRecords\":1,\"minValues\":{\"window\":{\"start\":\"2026-05-10T21:04:00.000Z\",\"end\":\"2026-05-10T21:05:00.000Z\"},\"olay_tipi\":\"purchase\",\"count\":16041},\"maxValues\":{\"window\":{\"start\":\"2026-05-10T21:04:00.000Z\",\"end\":\"2026-05-10T21:05:00.000Z\"},\"olay_tipi\":\"purchase\",\"count\":16041},\"nullCount\":{\"window\":{\"start\":0,\"end\":0},\"olay_tipi\":0,\"count\":0}}"}}
{"add":{"path":"part-00195-11011eae-441d-4e33-b205-8adb3560f8a2-c000.snappy.parquet","partitionValues":{},"size":1478,"modificationTime":1778447960560,"dataChange":true,"stats":"{\"numRecords\":1,\"minValues\":{\"window\":{\"start\":\"2026-05-10T21:00:00.000Z\",\"end\":\"2026-05-10T21:01:00.000Z\"},\"olay_tipi\":\"purchase\",\"count\":10455},\"maxValues\":{\"window\":{\"start\":\"2026-05-10T21:00:00.000Z\",\"end\":\"2026-05-10T21:01:00.000Z\"},\"olay_tipi\":\"purchase\",\"count\":10455},\"nullCount\":{\"window\":{\"start\":0,\"end\":0},\"olay_tipi\":0,\"count\":0}}"}}
{"add":{"path":"part-00198-bc5c3591-7593-4c09-818a-9071fe040685-c000.snappy.parquet","partitionValues":{},"size":1478,"modificationTime":1778447961183,"dataChange":true,"stats":"{\"numRecords\":1,\"minValues\":{\"window\":{\"start\":\"2026-05-10T19:45:00.000Z\",\"end\":\"2026-05-10T19:46:00.000Z\"},\"olay_tipi\":\"purchase\",\"count\":33948},\"maxValues\":{\"window\":{\"start\":\"2026-05-10T19:45:00.000Z\",\"end\":\"2026-05-10T19:46:00.000Z\"},\"olay_tipi\":\"purchase\",\"count\":33948},\"nullCount\":{\"window\":{\"start\":0,\"end\":0},\"olay_tipi\":0,\"count\":0}}"}}
{"remove":{"path":"part-00011-5092a563-f171-4bd5-9fcc-5c50efda350c-c000.snappy.parquet","deletionTimestamp":1778447890575,"dataChange":true,"extendedFileMetadata":true,"partitionValues":{},"size":1478}}
{"remove":{"path":"part-00195-da0d1b81-27f2-43c7-a424-25f68da64bc3-c000.snappy.parquet","deletionTimestamp":1778447890575,"dataChange":true,"extendedFileMetadata":true,"partitionValues":{},"size":1478}}
{"remove":{"path":"part-00029-b0f230d5-3b1e-4cf7-be2f-23e99c9bee28-c000.snappy.parquet","deletionTimestamp":1778447890575,"dataChange":true,"extendedFileMetadata":true,"partitionValues":{},"size":1478}}
{"remove":{"path":"part-00105-3bc2ef2a-dc0c-44d8-ba39-c694e8d362c4-c000.snappy.parquet","deletionTimestamp":1778447890575,"dataChange":true,"extendedFileMetadata":true,"partitionValues":{},"size":1478}}
{"remove":{"path":"part-00049-e8977e2d-aa53-44f2-89ad-85d1c985750b-c000.snappy.parquet","deletionTimestamp":1778447890575,"dataChange":true,"extendedFileMetadata":true,"partitionValues":{},"size":1478}}
{"remove":{"path":"part-00166-b19e5b44-7c3e-4234-ae3a-6e9a7ea37763-c000.snappy.parquet","deletionTimestamp":1778447890575,"dataChange":true,"extendedFileMetadata":true,"partitionValues":{},"size":1478}}
{"remove":{"path":"part-00189-1ea001fc-87f2-4d92-8b3b-bb0e8f751dbe-c000.snappy.parquet","deletionTimestamp":1778447890575,"dataChange":true,"extendedFileMetadata":true,"partitionValues":{},"size":1478}}
{"remove":{"path":"part-00010-f05de116-71d1-4fa0-b78d-e64c2ee3ac42-c000.snappy.parquet","deletionTimestamp":1778447890575,"dataChange":true,"extendedFileMetadata":true,"partitionValues":{},"size":1478}}
{"remove":{"path":"part-00192-1ae3a70c-63eb-4b6d-9a3f-76fc58d0715d-c000.snappy.parquet","deletionTimestamp":1778447890575,"dataChange":true,"extendedFileMetadata":true,"partitionValues":{},"size":1478}}
{"remove":{"path":"part-00023-d0a68dbb-9907-4af7-9c2c-69f0bf6b596e-c000.snappy.parquet","deletionTimestamp":1778447890575,"dataChange":true,"extendedFileMetadata":true,"partitionValues":{},"size":1477}}
{"remove":{"path":"part-00157-a54268d3-e2f9-4553-821c-e3ce23e3aad5-c000.snappy.parquet","deletionTimestamp":1778447890575,"dataChange":true,"extendedFileMetadata":true,"partitionValues":{},"size":1478}}
{"remove":{"path":"part-00158-0b026b56-8f8e-440a-83b4-b0bd147f3f5f-c000.snappy.parquet","deletionTimestamp":1778447890575,"dataChange":true,"extendedFileMetadata":true,"partitionValues":{},"size":1478}}
{"remove":{"path":"part-00017-77c697ad-78d8-45c7-922f-97d845c40dc0-c000.snappy.parquet","deletionTimestamp":1778447890575,"dataChange":true,"extendedFileMetadata":true,"partitionValues":{},"size":1436}}
{"remove":{"path":"part-00180-9722ec81-2ae6-46b2-902a-077c9e450a12-c000.snappy.parquet","deletionTimestamp":1778447890575,"dataChange":true,"extendedFileMetadata":true,"partitionValues":{},"size":1478}}
{"remove":{"path":"part-00162-94519be3-b0fc-43b5-85c1-182c012b70d0-c000.snappy.parquet","deletionTimestamp":1778447890575,"dataChange":true,"extendedFileMetadata":true,"partitionValues":{},"size":1478}}
{"remove":{"path":"part-00177-c4870dc2-55a5-4dd3-a37e-a9af97eeef93-c000.snappy.parquet","deletionTimestamp":1778447890575,"dataChange":true,"extendedFileMetadata":true,"partitionValues":{},"size":1478}}
{"remove":{"path":"part-00062-169dd4fd-1b49-49c8-ba47-2f338369b3d9-c000.snappy.parquet","deletionTimestamp":1778447890575,"dataChange":true,"extendedFileMetadata":true,"partitionValues":{},"size":1478}}
{"remove":{"path":"part-00124-48183079-9d47-400e-b177-871981d3ca43-c000.snappy.parquet","deletionTimestamp":1778447890575,"dataChange":true,"extendedFileMetadata":true,"partitionValues":{},"size":1478}}
{"remove":{"path":"part-00131-2b2186df-41b7-4300-b6bf-e98fdd7d4fc8-c000.snappy.parquet","deletionTimestamp":1778447890575,"dataChange":true,"extendedFileMetadata":true,"partitionValues":{},"size":1478}}
{"remove":{"path":"part-00065-a8bd150c-46db-47a9-bc91-c12700f1c72c-c000.snappy.parquet","deletionTimestamp":1778447890575,"dataChange":true,"extendedFileMetadata":true,"partitionValues":{},"size":1477}}
{"remove":{"path":"part-00108-1add014e-8e3c-473b-b4a7-0f3f58511c3f-c000.snappy.parquet","deletionTimestamp":1778447890575,"dataChange":true,"extendedFileMetadata":true,"partitionValues":{},"size":1478}}
{"remove":{"path":"part-00142-f0d072de-1318-4b06-965c-6a3f78f72b9e-c000.snappy.parquet","deletionTimestamp":1778447890575,"dataChange":true,"extendedFileMetadata":true,"partitionValues":{},"size":1478}}
{"remove":{"path":"part-00075-767381c4-56d5-40a4-a455-a46125328eea-c000.snappy.parquet","deletionTimestamp":1778447890575,"dataChange":true,"extendedFileMetadata":true,"partitionValues":{},"size":1478}}
{"remove":{"path":"part-00107-7eb2b38e-97ce-4bef-a6b5-fc58b28d867e-c000.snappy.parquet","deletionTimestamp":1778447890575,"dataChange":true,"extendedFileMetadata":true,"partitionValues":{},"size":1478}}
{"remove":{"path":"part-00187-c1cb7052-2221-4359-97f2-8141e83aadb0-c000.snappy.parquet","deletionTimestamp":1778447890575,"dataChange":true,"extendedFileMetadata":true,"partitionValues":{},"size":1436}}
{"remove":{"path":"part-00009-5db678e2-496f-4326-b18d-d272e051181a-c000.snappy.parquet","deletionTimestamp":1778447890575,"dataChange":true,"extendedFileMetadata":true,"partitionValues":{},"size":1477}}
{"remove":{"path":"part-00119-ac137d25-8d08-46b0-a205-50f1bae0d7c3-c000.snappy.parquet","deletionTimestamp":1778447890575,"dataChange":true,"extendedFileMetadata":true,"partitionValues":{},"size":1478}}
{"remove":{"path":"part-00198-e79729fe-9bc8-4739-ae57-7c701eae2479-c000.snappy.parquet","deletionTimestamp":1778447890575,"dataChange":true,"extendedFileMetadata":true,"partitionValues":{},"size":1478}}
{"remove":{"path":"part-00083-11ed2211-b5e1-470b-af74-2d9829ff73e9-c000.snappy.parquet","deletionTimestamp":1778447890575,"dataChange":true,"extendedFileMetadata":true,"partitionValues":{},"size":1478}}
{"remove":{"path":"part-00086-681d0938-142b-47d3-8dcd-228e794b13b4-c000.snappy.parquet","deletionTimestamp":1778447890575,"dataChange":true,"extendedFileMetadata":true,"partitionValues":{},"size":1478}}
{"remove":{"path":"part-00191-d7a30908-ec9c-4da9-8be5-74a7955a2176-c000.snappy.parquet","deletionTimestamp":1778447890575,"dataChange":true,"extendedFileMetadata":true,"partitionValues":{},"size":1478}}
{"remove":{"path":"part-00167-effed8ad-f936-4957-b7d4-70ed4528e328-c000.snappy.parquet","deletionTimestamp":1778447890575,"dataChange":true,"extendedFileMetadata":true,"partitionValues":{},"size":1478}}
{"remove":{"path":"part-00102-28362cea-1fe2-42b8-b8bd-c71ad2839c34-c000.snappy.parquet","deletionTimestamp":1778447890575,"dataChange":true,"extendedFileMetadata":true,"partitionValues":{},"size":1478}}
{"remove":{"path":"part-00002-52411e6f-b54e-4303-9fc5-e442e767fd32-c000.snappy.parquet","deletionTimestamp":1778447890575,"dataChange":true,"extendedFileMetadata":true,"partitionValues":{},"size":1478}}
{"remove":{"path":"part-00024-144c11eb-baeb-4e51-9e03-d9fffd46d227-c000.snappy.parquet","deletionTimestamp":1778447890575,"dataChange":true,"extendedFileMetadata":true,"partitionValues":{},"size":1478}}
